{
    "quizzes": [
        {
            "id": "2016015",
            "mondai": "分散処理システムに関する記述のうち，アクセス透過性を説明したものはどれか。",
            "sentaku": [
                "遠隔地にある資源を，遠隔地での処理方式を知らなくても，手元にある資源と同じ操作で利用できる。",
                "システムの運用と管理をそれぞれの組織で個別に行うことによって，その組織の実態に合ったサービスを提供することができる。",
                "集中して処理せずに，データの発生場所やサービスの要求場所で処理することによって，通信コストを削減できる。",
                "対等な関係のコンピュータが複数あるので，一部が故障しても他のコンピュータによる処理が可能となり，システム全体の信頼性を向上させることができる。"
            ],
            "answer": 0
        }
    ]
}