{
    "quizzes": [
        {
            "id": "2018102",
            "mondai": "次に示す手順は，列中の少なくとも一つは1であるビット列が与えられたとき，最も右にある1を残し，他のビットを全て0にするアルゴリズムである。例えば,00101000が与えられたとき,00001000が求まる。aに入る論理演算はどれか。\n手順1\n与えられたビット列Aを符号なしの2進数と見なし，Aから1を引き，結果をBとする。\n手順2\nAとBの排他的論理和(XOR)を求め，結果をCとする。\n手順3\nAとCの\na\nを求め，結果をAとする。",
            "sentaku": [
                "排他的論理和(XOR)",
                "否定論理積(NAND)",
                "論理積(AND)",
                "論理和(OR)"
            ],
            "answer": 2
        }
    ]
}